Metadata-Version: 2.1
Name: deut-repo-utils
Version: 0.1.dev1
Summary: Repository utilities to facilitate collaborative and modularized coding.
Home-page: UNKNOWN
Author: Joshua Mathias
Author-email: joshuaamathias@gmail.com
License: MIT
Platform: UNKNOWN
Classifier: Natural Language :: English
Classifier: Programming Language :: Python
Classifier: Programming Language :: Python :: 3
Classifier: Programming Language :: Python :: 3.6
Classifier: Programming Language :: Python :: 3.7
Classifier: Programming Language :: Python :: 3.8
Classifier: Programming Language :: Python :: 3.9
Requires-Python: >=3.6
Requires-Dist: GitPython
Requires-Dist: fire
Requires-Dist: pytest
Provides-Extra: all
Requires-Dist: identify (>=1.4.20) ; extra == 'all'
Requires-Dist: myst-parser ; extra == 'all'
Requires-Dist: pre-commit ; extra == 'all'
Requires-Dist: pypandoc (>=1.6.3) ; extra == 'all'
Requires-Dist: pytest ; extra == 'all'
Requires-Dist: pytest-cov ; extra == 'all'
Requires-Dist: pytest-flake8 ; extra == 'all'
Requires-Dist: sphinx ; extra == 'all'
Requires-Dist: sphinx-autobuild ; extra == 'all'
Requires-Dist: sphinx-book-theme ; extra == 'all'
Requires-Dist: watchdog (<1.0.0) ; (python_version < "3.6") and extra == 'all'
Requires-Dist: black (==21.7b0) ; (python_version >= "3.6") and extra == 'all'
Requires-Dist: readthedocs-sphinx-search ; (python_version >= "3.6") and extra == 'all'
Provides-Extra: dev
Requires-Dist: identify (>=1.4.20) ; extra == 'dev'
Requires-Dist: pre-commit ; extra == 'dev'
Requires-Dist: black (==21.7b0) ; (python_version >= "3.6") and extra == 'dev'
Provides-Extra: docs
Requires-Dist: myst-parser ; extra == 'docs'
Requires-Dist: pypandoc (>=1.6.3) ; extra == 'docs'
Requires-Dist: sphinx ; extra == 'docs'
Requires-Dist: sphinx-autobuild ; extra == 'docs'
Requires-Dist: sphinx-book-theme ; extra == 'docs'
Requires-Dist: watchdog (<1.0.0) ; (python_version < "3.6") and extra == 'docs'
Requires-Dist: readthedocs-sphinx-search ; (python_version >= "3.6") and extra == 'docs'
Provides-Extra: test
Requires-Dist: pytest ; extra == 'test'
Requires-Dist: pytest-cov ; extra == 'test'
Requires-Dist: pytest-flake8 ; extra == 'test'
